<?xml version="1.0" encoding="UTF-8"?>
<con:resource name="" path="/transactions" id="58613d1e-9add-4b5a-9bb4-76e02ef182cf" xmlns:xsi="http://www.w3.org/2001/XMLSchema-instance" xmlns:con="http://eviware.com/soapui/config">
  <con:settings>
    <con:setting id="58613d1e-9add-4b5a-9bb4-76e02ef182cffileName">%2Ftransactions</con:setting>
  </con:settings>
  <con:parameters/>
  <con:resource name="" path="{transactionId}" id="259aa1c1-b2ef-442e-a43f-dff7c4a91fb2">
    <con:settings/>
    <con:parameters>
      <con:parameter>
        <con:name>transactionId</con:name>
        <con:value xsi:nil="true"/>
        <con:style>TEMPLATE</con:style>
        <con:type xmlns:typ="http://gps.telefonica.com/types" xmlns:typ1="http://gps.telefonica.com/v1/types">typ1:transactionId</con:type>
        <con:default xsi:nil="true"/>
      </con:parameter>
    </con:parameters>
    <con:resource name="" path="/capture" id="2487e4a0-16c7-4f99-8c11-2fb068312486">
      <con:settings/>
      <con:parameters/>
      <con:method name="captureTransaction" id="230b4e00-368a-4321-8f08-6378576f2f16" method="PATCH">
        <con:settings/>
        <con:parameters/>
        <con:representation type="REQUEST" id="">
          <con:mediaType>application/json</con:mediaType>
          <con:status/>
          <con:params/>
          <con:description xsi:nil="true"/>
          <con:sampleContent xsi:nil="true"/>
        </con:representation>
        <con:representation type="REQUEST" id="">
          <con:mediaType>application/xml</con:mediaType>
          <con:status/>
          <con:params/>
          <con:description xsi:nil="true"/>
          <con:sampleContent xsi:nil="true"/>
        </con:representation>
        <con:representation type="RESPONSE" id="">
          <con:mediaType>application/json</con:mediaType>
          <con:status/>
          <con:params/>
          <con:description xsi:nil="true"/>
          <con:sampleContent xsi:nil="true"/>
        </con:representation>
        <con:representation type="RESPONSE" id="">
          <con:mediaType>application/xml</con:mediaType>
          <con:status/>
          <con:params/>
          <con:element>transaction</con:element>
          <con:description xsi:nil="true"/>
          <con:sampleContent xsi:nil="true"/>
        </con:representation>
        <con:representation type="RESPONSE" id="">
          <con:mediaType>application/json</con:mediaType>
          <con:status/>
          <con:params/>
          <con:description xsi:nil="true"/>
          <con:sampleContent xsi:nil="true"/>
        </con:representation>
        <con:representation type="RESPONSE" id="">
          <con:mediaType>application/xml</con:mediaType>
          <con:status/>
          <con:params/>
          <con:element>transaction</con:element>
          <con:description xsi:nil="true"/>
          <con:sampleContent xsi:nil="true"/>
        </con:representation>
        <con:representation type="RESPONSE" id="">
          <con:mediaType>application/json</con:mediaType>
          <con:status/>
          <con:params/>
          <con:description xsi:nil="true"/>
          <con:sampleContent xsi:nil="true"/>
        </con:representation>
        <con:representation type="RESPONSE" id="">
          <con:mediaType>application/xml</con:mediaType>
          <con:status/>
          <con:params/>
          <con:element>transaction</con:element>
          <con:description xsi:nil="true"/>
          <con:sampleContent xsi:nil="true"/>
        </con:representation>
        <con:representation type="RESPONSE" id="">
          <con:mediaType>application/json</con:mediaType>
          <con:status/>
          <con:params/>
          <con:description xsi:nil="true"/>
          <con:sampleContent xsi:nil="true"/>
        </con:representation>
        <con:representation type="RESPONSE" id="">
          <con:mediaType>application/xml</con:mediaType>
          <con:status/>
          <con:params/>
          <con:element>transaction</con:element>
          <con:description xsi:nil="true"/>
          <con:sampleContent xsi:nil="true"/>
        </con:representation>
        <con:representation type="RESPONSE" id="">
          <con:mediaType>application/json</con:mediaType>
          <con:status/>
          <con:params/>
          <con:description xsi:nil="true"/>
          <con:sampleContent xsi:nil="true"/>
        </con:representation>
        <con:representation type="RESPONSE" id="">
          <con:mediaType>application/xml</con:mediaType>
          <con:status/>
          <con:params/>
          <con:element>transaction</con:element>
          <con:description xsi:nil="true"/>
          <con:sampleContent xsi:nil="true"/>
        </con:representation>
        <con:representation type="RESPONSE" id="">
          <con:mediaType>application/json</con:mediaType>
          <con:status/>
          <con:params/>
          <con:description xsi:nil="true"/>
          <con:sampleContent xsi:nil="true"/>
        </con:representation>
        <con:representation type="RESPONSE" id="">
          <con:mediaType>application/xml</con:mediaType>
          <con:status/>
          <con:params/>
          <con:element>transaction</con:element>
          <con:description xsi:nil="true"/>
          <con:sampleContent xsi:nil="true"/>
        </con:representation>
        <con:representation type="RESPONSE" id="">
          <con:mediaType>application/json</con:mediaType>
          <con:status/>
          <con:params/>
          <con:description xsi:nil="true"/>
          <con:sampleContent xsi:nil="true"/>
        </con:representation>
        <con:representation type="RESPONSE" id="">
          <con:mediaType>application/xml</con:mediaType>
          <con:status/>
          <con:params/>
          <con:element>transaction</con:element>
          <con:description xsi:nil="true"/>
          <con:sampleContent xsi:nil="true"/>
        </con:representation>
        <con:request name="Request 1" id="36e713a4-9fce-4833-a1db-d485d96b6e9e" mediaType="application/json" postQueryString="false">
          <con:description xsi:nil="true"/>
          <con:settings>
            <con:setting id="com.eviware.soapui.impl.wsdl.WsdlRequest@request-headers">&lt;xml-fragment/></con:setting>
          </con:settings>
          <con:endpoint>http://localhost:8090</con:endpoint>
          <con:request>&lt;captureParameters>
  &lt;correlationId>BP1234821656590&lt;/correlationId>
&lt;/captureParameters></con:request>
          <con:originalUri>http://localhost/gps/v1/transactions/capture</con:originalUri>
          <con:credentials>
            <con:selectedAuthProfile>No Authorization</con:selectedAuthProfile>
            <con:authType>No Authorization</con:authType>
          </con:credentials>
          <con:jmsConfig JMSDeliveryMode="PERSISTENT"/>
          <con:parameters>
            <con:entry key="transactionId" value=""/>
          </con:parameters>
          <con:environmentSpec>
            <con:entry environmentId="e385afea-1153-4d90-83b9-3b49a724f0ea">
              <con:authProfile>Inherit From Parent</con:authProfile>
            </con:entry>
          </con:environmentSpec>
        </con:request>
        <con:environmentSpec>
          <con:entry environmentId="e385afea-1153-4d90-83b9-3b49a724f0ea">
            <con:authProfile>Inherit From Parent</con:authProfile>
          </con:entry>
        </con:environmentSpec>
      </con:method>
      <con:environmentSpec>
        <con:entry environmentId="e385afea-1153-4d90-83b9-3b49a724f0ea">
          <con:authProfile>Inherit From Parent</con:authProfile>
        </con:entry>
      </con:environmentSpec>
    </con:resource>
    <con:resource name="" path="/cancel" id="438270ac-67fd-4162-9879-fa9e6ac6bfaf">
      <con:settings/>
      <con:parameters/>
      <con:method name="cancelTransaction" id="cc0ef660-0acb-4876-b20a-5f3444709ac6" method="PATCH">
        <con:settings/>
        <con:parameters/>
        <con:representation type="RESPONSE" id="">
          <con:mediaType>application/json</con:mediaType>
          <con:status/>
          <con:params/>
          <con:description xsi:nil="true"/>
          <con:sampleContent xsi:nil="true"/>
        </con:representation>
        <con:representation type="RESPONSE" id="">
          <con:mediaType>application/xml</con:mediaType>
          <con:status/>
          <con:params/>
          <con:element>transaction</con:element>
          <con:description xsi:nil="true"/>
          <con:sampleContent xsi:nil="true"/>
        </con:representation>
        <con:representation type="RESPONSE" id="">
          <con:mediaType>application/json</con:mediaType>
          <con:status/>
          <con:params/>
          <con:description xsi:nil="true"/>
          <con:sampleContent xsi:nil="true"/>
        </con:representation>
        <con:representation type="RESPONSE" id="">
          <con:mediaType>application/xml</con:mediaType>
          <con:status/>
          <con:params/>
          <con:element>transaction</con:element>
          <con:description xsi:nil="true"/>
          <con:sampleContent xsi:nil="true"/>
        </con:representation>
        <con:representation type="RESPONSE" id="">
          <con:mediaType>application/json</con:mediaType>
          <con:status/>
          <con:params/>
          <con:description xsi:nil="true"/>
          <con:sampleContent xsi:nil="true"/>
        </con:representation>
        <con:representation type="RESPONSE" id="">
          <con:mediaType>application/xml</con:mediaType>
          <con:status/>
          <con:params/>
          <con:element>transaction</con:element>
          <con:description xsi:nil="true"/>
          <con:sampleContent xsi:nil="true"/>
        </con:representation>
        <con:representation type="RESPONSE" id="">
          <con:mediaType>application/json</con:mediaType>
          <con:status/>
          <con:params/>
          <con:description xsi:nil="true"/>
          <con:sampleContent xsi:nil="true"/>
        </con:representation>
        <con:representation type="RESPONSE" id="">
          <con:mediaType>application/xml</con:mediaType>
          <con:status/>
          <con:params/>
          <con:element>transaction</con:element>
          <con:description xsi:nil="true"/>
          <con:sampleContent xsi:nil="true"/>
        </con:representation>
        <con:representation type="RESPONSE" id="">
          <con:mediaType>application/json</con:mediaType>
          <con:status/>
          <con:params/>
          <con:description xsi:nil="true"/>
          <con:sampleContent xsi:nil="true"/>
        </con:representation>
        <con:representation type="RESPONSE" id="">
          <con:mediaType>application/xml</con:mediaType>
          <con:status/>
          <con:params/>
          <con:element>transaction</con:element>
          <con:description xsi:nil="true"/>
          <con:sampleContent xsi:nil="true"/>
        </con:representation>
        <con:representation type="RESPONSE" id="">
          <con:mediaType>application/json</con:mediaType>
          <con:status/>
          <con:params/>
          <con:description xsi:nil="true"/>
          <con:sampleContent xsi:nil="true"/>
        </con:representation>
        <con:representation type="RESPONSE" id="">
          <con:mediaType>application/xml</con:mediaType>
          <con:status/>
          <con:params/>
          <con:element>transaction</con:element>
          <con:description xsi:nil="true"/>
          <con:sampleContent xsi:nil="true"/>
        </con:representation>
        <con:request name="Request 1" id="f1fa6059-cb3e-4a57-b4e0-b8039ccc3da4" mediaType="application/json" postQueryString="false">
          <con:description xsi:nil="true"/>
          <con:settings>
            <con:setting id="com.eviware.soapui.impl.wsdl.WsdlRequest@request-headers">&lt;xml-fragment/></con:setting>
          </con:settings>
          <con:endpoint>http://localhost:8090</con:endpoint>
          <con:request/>
          <con:originalUri>http://localhost/gps/v1/transactions/123/cancel</con:originalUri>
          <con:credentials>
            <con:selectedAuthProfile>No Authorization</con:selectedAuthProfile>
            <con:authType>No Authorization</con:authType>
          </con:credentials>
          <con:jmsConfig JMSDeliveryMode="PERSISTENT"/>
          <con:parameters>
            <con:entry key="transactionId" value="123"/>
          </con:parameters>
          <con:environmentSpec>
            <con:entry environmentId="e385afea-1153-4d90-83b9-3b49a724f0ea">
              <con:authProfile>Inherit From Parent</con:authProfile>
            </con:entry>
          </con:environmentSpec>
        </con:request>
        <con:environmentSpec>
          <con:entry environmentId="e385afea-1153-4d90-83b9-3b49a724f0ea">
            <con:authProfile>Inherit From Parent</con:authProfile>
          </con:entry>
        </con:environmentSpec>
      </con:method>
      <con:environmentSpec>
        <con:entry environmentId="e385afea-1153-4d90-83b9-3b49a724f0ea">
          <con:authProfile>Inherit From Parent</con:authProfile>
        </con:entry>
      </con:environmentSpec>
    </con:resource>
    <con:method name="getTransactionById" id="2df3b061-b7c9-4e31-a5e9-b19a6ff29455" method="GET">
      <con:settings/>
      <con:parameters/>
      <con:representation type="RESPONSE" id="">
        <con:mediaType>application/json</con:mediaType>
        <con:status/>
        <con:params/>
        <con:description xsi:nil="true"/>
        <con:sampleContent xsi:nil="true"/>
      </con:representation>
      <con:representation type="RESPONSE" id="">
        <con:mediaType>application/xml</con:mediaType>
        <con:status/>
        <con:params/>
        <con:element>transaction</con:element>
        <con:description xsi:nil="true"/>
        <con:sampleContent xsi:nil="true"/>
      </con:representation>
      <con:representation type="RESPONSE" id="">
        <con:mediaType>application/json</con:mediaType>
        <con:status/>
        <con:params/>
        <con:description xsi:nil="true"/>
        <con:sampleContent xsi:nil="true"/>
      </con:representation>
      <con:representation type="RESPONSE" id="">
        <con:mediaType>application/xml</con:mediaType>
        <con:status/>
        <con:params/>
        <con:element>transaction</con:element>
        <con:description xsi:nil="true"/>
        <con:sampleContent xsi:nil="true"/>
      </con:representation>
      <con:representation type="RESPONSE" id="">
        <con:mediaType>application/json</con:mediaType>
        <con:status/>
        <con:params/>
        <con:description xsi:nil="true"/>
        <con:sampleContent xsi:nil="true"/>
      </con:representation>
      <con:representation type="RESPONSE" id="">
        <con:mediaType>application/xml</con:mediaType>
        <con:status/>
        <con:params/>
        <con:element>transaction</con:element>
        <con:description xsi:nil="true"/>
        <con:sampleContent xsi:nil="true"/>
      </con:representation>
      <con:representation type="RESPONSE" id="">
        <con:mediaType>application/json</con:mediaType>
        <con:status/>
        <con:params/>
        <con:description xsi:nil="true"/>
        <con:sampleContent xsi:nil="true"/>
      </con:representation>
      <con:representation type="RESPONSE" id="">
        <con:mediaType>application/xml</con:mediaType>
        <con:status/>
        <con:params/>
        <con:element>transaction</con:element>
        <con:description xsi:nil="true"/>
        <con:sampleContent xsi:nil="true"/>
      </con:representation>
      <con:representation type="RESPONSE" id="">
        <con:mediaType>application/json</con:mediaType>
        <con:status/>
        <con:params/>
        <con:description xsi:nil="true"/>
        <con:sampleContent xsi:nil="true"/>
      </con:representation>
      <con:representation type="RESPONSE" id="">
        <con:mediaType>application/xml</con:mediaType>
        <con:status/>
        <con:params/>
        <con:element>transaction</con:element>
        <con:description xsi:nil="true"/>
        <con:sampleContent xsi:nil="true"/>
      </con:representation>
      <con:request name="Request 1" id="600d8f67-4d66-4d51-b079-012da8946fb3" mediaType="application/json">
        <con:description xsi:nil="true"/>
        <con:settings>
          <con:setting id="com.eviware.soapui.impl.wsdl.WsdlRequest@request-headers">&lt;xml-fragment/></con:setting>
        </con:settings>
        <con:endpoint>http://localhost:8090</con:endpoint>
        <con:request/>
        <con:originalUri>http://localhost/gps/v1/transactions/</con:originalUri>
        <con:credentials>
          <con:selectedAuthProfile>No Authorization</con:selectedAuthProfile>
          <con:authType>No Authorization</con:authType>
        </con:credentials>
        <con:jmsConfig JMSDeliveryMode="PERSISTENT"/>
        <con:parameters>
          <con:entry key="transactionId" value="123"/>
        </con:parameters>
        <con:environmentSpec>
          <con:entry environmentId="e385afea-1153-4d90-83b9-3b49a724f0ea">
            <con:authProfile>Inherit From Parent</con:authProfile>
          </con:entry>
        </con:environmentSpec>
      </con:request>
      <con:environmentSpec>
        <con:entry environmentId="e385afea-1153-4d90-83b9-3b49a724f0ea">
          <con:authProfile>Inherit From Parent</con:authProfile>
        </con:entry>
      </con:environmentSpec>
    </con:method>
    <con:environmentSpec>
      <con:entry environmentId="e385afea-1153-4d90-83b9-3b49a724f0ea">
        <con:authProfile>Inherit From Parent</con:authProfile>
      </con:entry>
    </con:environmentSpec>
  </con:resource>
  <con:environmentSpec>
    <con:entry environmentId="e385afea-1153-4d90-83b9-3b49a724f0ea">
      <con:authProfile>Inherit From Parent</con:authProfile>
    </con:entry>
  </con:environmentSpec>
</con:resource>
