<?xml version="1.0" encoding="UTF-8"?>
<con:operation id="135552da-a7c3-4223-be2a-776e154da0ad" isOneWay="false" action="" name="topupSynchronous" bindingOperationName="topupSynchronous" type="Request-Response" outputName="topupSynchronousResponse" inputName="topupSynchronous" receivesAttachments="false" sendsAttachments="false" anonymous="optional" xmlns:xsi="http://www.w3.org/2001/XMLSchema-instance" xmlns:con="http://eviware.com/soapui/config">
  <con:settings>
    <con:setting id="135552da-a7c3-4223-be2a-776e154da0adfileName">topupSynchronous</con:setting>
  </con:settings>
  <con:call id="672a28aa-bdf2-4694-8c49-72742699aa68" name="Request 1">
    <con:settings>
      <con:setting id="com.eviware.soapui.impl.wsdl.WsdlRequest@request-headers">&lt;xml-fragment/></con:setting>
    </con:settings>
    <con:encoding>UTF-8</con:encoding>
    <con:endpoint>${#Project#drc-DirectRechargeEvolutionServiceForMobilcomDebitel-URL}</con:endpoint>
    <con:request><![CDATA[<soapenv:Envelope xmlns:soapenv="http://schemas.xmlsoap.org/soap/envelope/" xmlns:mode="http://directrecharge.o2.com/ws/directrechargeevolutionservice/topupsynchronous/mode/">
   <soapenv:Header/>
   <soapenv:Body>
      <mode:topupSynchronous>
         <DirectRechargeServiceTopupDto>
            <!--type: amount-->
            <amount>3</amount>
            <!--type: balanceType - enumeration: [1,2,3,4,5,6]-->
            <balanceType>2</balanceType>
            <!--Optional:-->
            <!--type: currency - enumeration: [EUR]-->
            <currency>EUR</currency>
            <!--Optional:-->
            <!--type: dateTime-->
            <gratificationDate>2007-10-26T08:36:28</gratificationDate>
            <!--type: msisdn-->
            <msisdn>quae divum incedo</msisdn>
            <!--type: referenceId-->
            <referenceId>verrantque per auras</referenceId>
            <!--Optional:-->
            <!--type: serviceProviderId-->
            <subscriptionId>per auras</subscriptionId>
            <!--Optional:-->
            <!--type: paymentUseCase-->
            <paymentUseCase>FULL_WITH_SMS</paymentUseCase>
            <!--type: terminalId-->
            <terminalId>circum c</terminalId>
            <!--type: terminalTimestamp-->
            <terminalTimestamp>2003-08-09T02:18:37+02:00</terminalTimestamp>
            <!--type: terminalTraceNum-->
            <terminalTraceNum>ferant ra</terminalTraceNum>
            <!--type: serverId-->
            <serverId>sceptr</serverId>
            <!--type: processingId-->
            <processingId>turbine corripuit scopuloque</processingId>
            <!--type: partnerId-->
            <partnerId>flammato secum</partnerId>
         </DirectRechargeServiceTopupDto>
      </mode:topupSynchronous>
   </soapenv:Body>
</soapenv:Envelope>]]></con:request>
    <con:credentials>
      <con:selectedAuthProfile>No Authorization</con:selectedAuthProfile>
      <con:authType>No Authorization</con:authType>
    </con:credentials>
    <con:jmsConfig JMSDeliveryMode="PERSISTENT"/>
    <con:wsaConfig mustUnderstand="NONE" version="200508" action="http://directrecharge.o2.com/ws/directrechargeevolutionservice/DirectRechargeEvolutionServiceForMoDePortType/topupSynchronous"/>
    <con:wsrmConfig version="1.2"/>
    <con:environmentSpec>
      <con:entry environmentId="ff1a32e2-ce69-4c5a-923a-710f216e83c9">
        <con:authProfile>No Authorization</con:authProfile>
      </con:entry>
      <con:entry environmentId="96753c0f-e806-4b6f-b398-e4e8dbc7bce1">
        <con:authProfile>No Authorization</con:authProfile>
      </con:entry>
      <con:entry environmentId="d4fb7d9b-be04-4609-bf0a-ed3a22d5075f">
        <con:authProfile>No Authorization</con:authProfile>
      </con:entry>
      <con:entry environmentId="e385afea-1153-4d90-83b9-3b49a724f0ea">
        <con:authProfile>Inherit From Parent</con:authProfile>
      </con:entry>
    </con:environmentSpec>
  </con:call>
  <con:environmentSpec>
    <con:entry environmentId="e385afea-1153-4d90-83b9-3b49a724f0ea">
      <con:authProfile>Inherit From Parent</con:authProfile>
    </con:entry>
  </con:environmentSpec>
</con:operation>
