<?xml version="1.0" encoding="UTF-8"?>
<con:operation id="1bef89fe-91a9-428a-b2f8-7361311a6f4d" isOneWay="false" action="deductBalance" name="deductBalance" bindingOperationName="deductBalance" type="Request-Response" inputName="" receivesAttachments="false" sendsAttachments="false" anonymous="optional" xmlns:xsi="http://www.w3.org/2001/XMLSchema-instance" xmlns:con="http://eviware.com/soapui/config">
  <con:settings>
    <con:setting id="1bef89fe-91a9-428a-b2f8-7361311a6f4dfileName">deductBalance</con:setting>
  </con:settings>
  <con:call id="444a9cdf-c403-4a0e-a76f-21f05e17f8e9" defaultOutgoingWss="" defaultIncomingWss="" name="Request 1">
    <con:settings/>
    <con:encoding>UTF-8</con:encoding>
    <con:endpoint>http://localhost:8080/OCS10/BalanceManagementService</con:endpoint>
    <con:request><![CDATA[<soapenv:Envelope xmlns:soapenv="http://schemas.xmlsoap.org/soap/envelope/" xmlns:add="http://schemas.xmlsoap.org/ws/2004/08/addressing" xmlns:v1="http://www.telefonica.com/OCS/To2DE/OCS_types/v1_1">
   <soapenv:Header>
      <add:ReplyTo>
         <add:Address>http://www.my.com/flammas/ac</add:Address>
      </add:ReplyTo>
      <add:MessageID>http://www.any.org/speluncis/profundum</add:MessageID>
   </soapenv:Header>
   <soapenv:Body>
      <v1:deductBalanceRequest>
         <v1:appInfo>
            <!--type: ApplicationIdType-->
            <v1:applicationId>gero et</v1:applicationId>
            <!--type: ErReferenceType-->
            <v1:reference>sonoras imperio</v1:reference>
         </v1:appInfo>
         <v1:subscriberId>
            <!--You have a CHOICE of the next 4 items at this level-->
            <!--type: E164NumberType-->
            <v1:e164Number>quae divum incedo</v1:e164Number>
            <!--type: string-->
            <v1:userName>verrantque per auras</v1:userName>
            <!--type: anyURI-->
            <v1:anyURI>http://www.sample.org/turbine/circum</v1:anyURI>
            <v1:ipAddress>
               <!--You have a CHOICE of the next 2 items at this level-->
               <!--type: Ipv4AddressType-->
               <v1:ipv4Address>nimborum in</v1:ipv4Address>
               <!--type: Ipv6AddressType-->
               <v1:ipv6Address>foedere certo</v1:ipv6Address>
            </v1:ipAddress>
         </v1:subscriberId>
         <v1:amount exponent="3" currencyCode="profundum quippe ferant">3</v1:amount>
         <!--type: WalletIdType-->
         <v1:walletId>et carcere</v1:walletId>
         <!--type: boolean-->
         <v1:allOrNothingFlag>true</v1:allOrNothingFlag>
      </v1:deductBalanceRequest>
   </soapenv:Body>
</soapenv:Envelope>]]></con:request>
    <con:credentials>
      <con:selectedAuthProfile>No Authorization</con:selectedAuthProfile>
      <con:authType>No Authorization</con:authType>
    </con:credentials>
    <con:environmentSpec>
      <con:entry environmentId="18ada261-dd9a-45b4-9a95-6c2beddd0498">
        <con:authProfile>No Authorization</con:authProfile>
      </con:entry>
      <con:entry environmentId="8bb64a40-b6a3-45c2-a26b-7f6c797dbea5">
        <con:authProfile>No Authorization</con:authProfile>
      </con:entry>
      <con:entry environmentId="ff1a32e2-ce69-4c5a-923a-710f216e83c9">
        <con:authProfile>No Authorization</con:authProfile>
      </con:entry>
      <con:entry environmentId="96753c0f-e806-4b6f-b398-e4e8dbc7bce1">
        <con:authProfile>No Authorization</con:authProfile>
      </con:entry>
      <con:entry environmentId="d4fb7d9b-be04-4609-bf0a-ed3a22d5075f">
        <con:authProfile>No Authorization</con:authProfile>
      </con:entry>
      <con:entry environmentId="e385afea-1153-4d90-83b9-3b49a724f0ea">
        <con:authProfile>Inherit From Parent</con:authProfile>
      </con:entry>
    </con:environmentSpec>
    <con:jmsConfig JMSDeliveryMode="PERSISTENT"/>
    <con:wsaConfig mustUnderstand="NONE" version="200508" action="deductBalance"/>
    <con:wsrmConfig version="1.2"/>
  </con:call>
  <con:environmentSpec>
    <con:entry environmentId="e385afea-1153-4d90-83b9-3b49a724f0ea">
      <con:authProfile>Inherit From Parent</con:authProfile>
    </con:entry>
  </con:environmentSpec>
</con:operation>
